{
  "main": {
    "id": "5af6db01628bcc75",
    "type": "split",
    "children": [
      {
        "id": "da1c5c6345b86f1f",
        "type": "tabs",
        "children": [
          {
            "id": "e1682dbb1d130493",
            "type": "leaf",
            "state": {
              "type": "markdown",
              "state": {
                "file": "HTB/Linux Fundamentals.md",
                "mode": "source",
                "source": false
              }
            }
          },
          {
            "id": "645d58812f952e6a",
            "type": "leaf",
            "state": {
              "type": "markdown",
              "state": {
                "file": "LINUX/NOTES.md",
                "mode": "source",
                "source": false
              }
            }
          }
        ],
        "currentTab": 1
      }
    ],
    "direction": "vertical"
  },
  "left": {
    "id": "42db5b1b2ab22de4",
    "type": "split",
    "children": [
      {
        "id": "f589854b268bad48",
        "type": "tabs",
        "children": [
          {
            "id": "959124312836be08",
            "type": "leaf",
            "state": {
              "type": "file-explorer",
              "state": {
                "sortOrder": "alphabetical"
              }
            }
          },
          {
            "id": "a5106b6bd3dba3c2",
            "type": "leaf",
            "state": {
              "type": "search",
              "state": {
                "query": "",
                "matchingCase": false,
                "explainSearch": false,
                "collapseAll": false,
                "extraContext": false,
                "sortOrder": "alphabetical"
              }
            }
          },
          {
            "id": "0da8b7e5488caca4",
            "type": "leaf",
            "state": {
              "type": "bookmarks",
              "state": {}
            }
          }
        ]
      }
    ],
    "direction": "horizontal",
    "width": 200,
    "collapsed": true
  },
  "right": {
    "id": "8683a5fd1ec57ddb",
    "type": "split",
    "children": [
      {
        "id": "bb1eea401db49e3f",
        "type": "tabs",
        "children": [
          {
            "id": "8f906dc822998c3e",
            "type": "leaf",
            "state": {
              "type": "backlink",
              "state": {
                "file": "LINUX/NOTES.md",
                "collapseAll": false,
                "extraContext": false,
                "sortOrder": "alphabetical",
                "showSearch": false,
                "searchQuery": "",
                "backlinkCollapsed": false,
                "unlinkedCollapsed": true
              }
            }
          },
          {
            "id": "cbbff9e94f88062a",
            "type": "leaf",
            "state": {
              "type": "outgoing-link",
              "state": {
                "file": "LINUX/NOTES.md",
                "linksCollapsed": false,
                "unlinkedCollapsed": true
              }
            }
          },
          {
            "id": "ada2ed32fab93fc4",
            "type": "leaf",
            "state": {
              "type": "tag",
              "state": {
                "sortOrder": "frequency",
                "useHierarchy": true
              }
            }
          },
          {
            "id": "a7ec0b52cbfd4821",
            "type": "leaf",
            "state": {
              "type": "outline",
              "state": {
                "file": "LINUX/NOTES.md"
              }
            }
          },
          {
            "id": "d152b45748c37703",
            "type": "leaf",
            "state": {
              "type": "advanced-tables-toolbar",
              "state": {}
            }
          }
        ],
        "currentTab": 4
      }
    ],
    "direction": "horizontal",
    "width": 300,
    "collapsed": true
  },
  "left-ribbon": {
    "hiddenItems": {
      "switcher:Open quick switcher": false,
      "graph:Open graph view": false,
      "canvas:Create new canvas": false,
      "daily-notes:Open today's daily note": false,
      "templates:Insert template": false,
      "command-palette:Open command palette": false,
      "table-editor-obsidian:Advanced Tables Toolbar": false
    }
  },
  "active": "645d58812f952e6a",
  "lastOpenFiles": [
    "HTB/Linux Fundamentals.md",
    "LINUX/NOTES.md",
    "BUG BOUNTY/NOTES.md",
    "Untitled 1.md",
    "LINUX/Over The Wire CTF.md",
    "Untitled.md",
    "PENTESTING/NOTES.md",
    "MASTERS DEGREE RESEARCH WORK.md",
    "RESEARCH WORKS",
    "THM/ADVENT OF CYBER 2022.md",
    "MSF/STUDY NOTE.md",
    "THM",
    "PENTESTING",
    "LINUX",
    "MSF",
    "HTB",
    "BUG BOUNTY"
  ]
}